[{
    "userId": "01",
    "name": "Luan Fonseca",
    "pass": "123",
    "balance": 10000.00,
    "image": "https://avatars.githubusercontent.com/u/51548623?s=400&u=6c03bee3e53d430785828694d2a80c498d8607d4&v=4",
    "listaDeConta": [{
            "bandeira": {
                "nome": "NuBank",
                "imagem": "https://nubank.com.br/images/nu-icon.png?v=2",
                "balance": 320.00
            },
            "criadoEm": "17/10/2020",
            "listaDeMovimentacao": [{
                "id": "1",
                "ehReceita": false,
                "diaDaMovimentacao": "05/09/2022",
                "valor": 320.00,
                "descricao": "Conta de Luz"
            }]
        },
        {
            "bandeira": {
                "nome": "PicPay",
                "imagem": "https://play-lh.googleusercontent.com/pTvc9kCumx_24eJDwGUpvcBwljcIBkrsL3qHwhBW2NalMQ-XxTtHRV9YAJanBxkV0Rw"
            },
            "criadoEm": "20/10/2020",
            "listaDeMovimentacao": [{
                "id": "1",
                "ehReceita": true,
                "diaDaMovimentacao": "09/09/2022",
                "valor": 1200.00,
                "descricao": "Extra"
            }]
        }
    ]
}]
